nr/__init__.py
nr/utils/__init__.py
nr/utils/ponyorm/__init__.py
nr/utils/ponyorm/appdb.py
nr/utils/ponyorm/converters.py
nr/utils/ponyorm/entity.py
nr/utils/ponyorm/utils.py
nr.utils.ponyorm-0.0.2.dist-info/LICENSE.txt
nr.utils.ponyorm-0.0.2.dist-info/METADATA
nr.utils.ponyorm-0.0.2.dist-info/WHEEL
nr.utils.ponyorm-0.0.2.dist-info/top_level.txt
nr.utils.ponyorm-0.0.2.dist-info/zip-safe
nr.utils.ponyorm-0.0.2.dist-info/RECORD
