Metadata-Version: 2.1
Name: nr.utils.ponyorm
Version: 0.0.2
Summary: Package description here.
Home-page: https://git.niklasrosenstein.com/NiklasRosenstein/nr
Author: Niklas Rosenstein
Author-email: rosensteinniklas@gmail.com
License: MIT
Platform: UNKNOWN
Requires-Python: >=3.4.0,<4.0.0
Requires-Dist: nr.pylang.utils (<1.0.0,>=0.0.1)
Requires-Dist: pony (<1.0.0,>=0.7.0)
